apertium_apy/__init__.py
apertium_apy/apy.py
apertium_apy/gateway.py
apertium_apy/keys.py
apertium_apy/missingdb.py
apertium_apy/mode_search.py
apertium_apy/systemd.py
apertium_apy/handlers/__init__.py
apertium_apy/handlers/analyze.py
apertium_apy/handlers/base.py
apertium_apy/handlers/coverage.py
apertium_apy/handlers/generate.py
apertium_apy/handlers/guesser.py
apertium_apy/handlers/identify_lang.py
apertium_apy/handlers/list_language_names.py
apertium_apy/handlers/list_modes.py
apertium_apy/handlers/per_word.py
apertium_apy/handlers/pipe_debug.py
apertium_apy/handlers/speller.py
apertium_apy/handlers/stats.py
apertium_apy/handlers/suggestion.py
apertium_apy/handlers/translate.py
apertium_apy/handlers/translate_chain.py
apertium_apy/handlers/translate_doc.py
apertium_apy/handlers/translate_raw.py
apertium_apy/handlers/translate_webpage.py
apertium_apy/utils/__init__.py
apertium_apy/utils/translation.py
apertium_apy/utils/wiki.py
apertium_apy-0.13.0.data/data/share/apertium-apy/COPYING
apertium_apy-0.13.0.data/data/share/apertium-apy/README.md
apertium_apy-0.13.0.data/data/share/apertium-apy/index.html
apertium_apy-0.13.0.data/data/share/apertium-apy/langNames.db
apertium_apy-0.13.0.data/data/share/apertium-apy/lid.beta.ftz
apertium_apy-0.13.0.data/data/share/apertium-apy/lid.release.ftz
apertium_apy-0.13.0.data/data/share/apertium-apy/tools/apertium-recaptcha-test.html
apertium_apy-0.13.0.data/data/share/apertium-apy/tools/apertium-viewer.html
apertium_apy-0.13.0.data/data/share/apertium-apy/tools/serverlist-example
apertium_apy-0.13.0.data/data/share/apertium-apy/tools/systemd/README
apertium_apy-0.13.0.data/data/share/apertium-apy/tools/systemd/apy.service
apertium_apy-0.13.0.data/data/share/apertium-apy/tools/sysvinit/apy.sh
apertium_apy-0.13.0.dist-info/licenses/COPYING
apertium_apy-0.13.0.dist-info/METADATA
apertium_apy-0.13.0.dist-info/WHEEL
apertium_apy-0.13.0.dist-info/entry_points.txt
apertium_apy-0.13.0.dist-info/top_level.txt
apertium_apy-0.13.0.dist-info/RECORD
