Metadata-Version: 2.4
Name: apertium-apy
Version: 0.13.0
Summary: Apertium Web Service
Home-page: https://github.com/apertium/apertium-apy
Author: Apertium
Author-email: sushain@skc.name
License: GPLv3
Keywords: apertium parsing linguistics server
Classifier: Development Status :: 4 - Beta
Classifier: Topic :: Text Processing :: Linguistic
Classifier: Topic :: Internet :: WWW/HTTP :: HTTP Servers
Classifier: License :: OSI Approved :: GNU General Public License v3 (GPLv3)
Classifier: Intended Audience :: Science/Research
Classifier: Intended Audience :: Developers
Classifier: Programming Language :: Python :: 3.8
Classifier: Programming Language :: Python :: 3.9
Classifier: Programming Language :: Python :: 3.10
Classifier: Programming Language :: Python :: 3.11
Classifier: Programming Language :: Python :: 3.12
Classifier: Programming Language :: Python :: 3 :: Only
Requires-Python: >=3.8
License-File: COPYING
Requires-Dist: tornado<7,>=4.2
Provides-Extra: spelling
Requires-Dist: apertium-streamparser; extra == "spelling"
Provides-Extra: suggestions
Requires-Dist: requests; extra == "suggestions"
Provides-Extra: website-encoding-detect
Requires-Dist: chardet; extra == "website-encoding-detect"
Provides-Extra: lang-detect
Requires-Dist: chromium_compact_language_detector; extra == "lang-detect"
Provides-Extra: pair-preferences
Requires-Dist: lxml; extra == "pair-preferences"
Provides-Extra: full
Requires-Dist: apertium-streamparser; extra == "full"
Requires-Dist: requests; extra == "full"
Requires-Dist: chardet; extra == "full"
Requires-Dist: chromium_compact_language_detector; extra == "full"
Requires-Dist: commentjson; extra == "full"
Requires-Dist: lxml; extra == "full"
Dynamic: author
Dynamic: author-email
Dynamic: classifier
Dynamic: description
Dynamic: description-content-type
Dynamic: home-page
Dynamic: keywords
Dynamic: license
Dynamic: license-file
Dynamic: provides-extra
Dynamic: requires-dist
Dynamic: requires-python
Dynamic: summary
